{"assets/fonts/GoogleSans-Bold.ttf":["assets/fonts/GoogleSans-Bold.ttf"],"assets/fonts/GoogleSans-BoldItalic.ttf":["assets/fonts/GoogleSans-BoldItalic.ttf"],"assets/fonts/GoogleSans-Italic.ttf":["assets/fonts/GoogleSans-Italic.ttf"],"assets/fonts/GoogleSans-Regular.ttf":["assets/fonts/GoogleSans-Regular.ttf"],"assets/images/ctw_logo.png":["assets/images/ctw_logo.png"],"assets/images/duck_full.png":["assets/images/duck_full.png"],"assets/images/heart_image.png":["assets/images/heart_image.png"],"assets/images/our_logo.png":["assets/images/our_logo.png"],"assets/images/quack_duck.gif":["assets/images/quack_duck.gif"],"assets/images/shuffle_icon.png":["assets/images/shuffle_icon.png"],"assets/images/square_bmw.jpg":["assets/images/square_bmw.jpg"],"assets/images/square_burger.jpeg":["assets/images/square_burger.jpeg"],"assets/images/square_dash.jpeg":["assets/images/square_dash.jpeg"],"assets/images/square_ducks.jpeg":["assets/images/square_ducks.jpeg"],"assets/images/square_mosaic.jpg":["assets/images/square_mosaic.jpg"],"assets/images/square_pizza.jpeg":["assets/images/square_pizza.jpeg"],"assets/images/square_png.png":["assets/images/square_png.png"],"assets/images/super_logo.png":["assets/images/super_logo.png"],"assets/images/walking_duck.gif":["assets/images/walking_duck.gif"]}